{
	"bio": {
		"name": "Venki Vijay"
	},
	"links": [
		{ "url": "https://venkivijay.com", "displayText": "Portfolio" },
		{ "url": "https://venkivijay.github.io/resume/Venkatesh-Developer-Resume.pdf", "displayText": "Resume" },
		{
			"button": "github",
			"icon": "github",
			"url": "https://github.com/venkivijay"
		},
		{
			"button": "linkedin",
			"icon": "linkedin",
			"url": "https://linkedin.com/in/venkivijay"
		},
		{
			"icon": "email",
			"url": "mailto:venkivijay@hotmail.com"
		},
		{
			"button": "whatsapp",
			"icon": "whatsapp",
			"url": "https://wa.me/+918122932334"
		},
		{
			"button": "facebook",
			"icon": "facebook",
			"url": "https://www.facebook.com/venki.vj.vijay"
		},
		{
			"button": "instagram",
			"icon": "instagram",
			"url": "https://www.instagram.com/venki.vj/"
		},
		{
			"button": "twitter",
			"icon": "twitter",
			"url": "https://twitter.com/venkivijay_"
		}
	]
}
